runpodmanager/RunPodManager.py
runpodmanager/__init__.py
runpodmanager-0.1.1.dist-info/WHEEL
runpodmanager-0.1.1.dist-info/METADATA
runpodmanager-0.1.1.dist-info/RECORD
