Metadata-Version: 2.3
Name: runpodmanager
Version: 0.1.1
Summary: Python library to manage RunPod pods
Requires-Dist: runpod>=1.7.13
Requires-Python: >=3.11
